[{"created_epoch": "1657221366000", "enumeration_type": "NPI-2", "last_updated_epoch": "1657221366000", "number": "1518690411", "addresses": [{"country_code": "US", "country_name": "United States", "address_purpose": "MAILING", "address_type": "DOM", "address_1": "2358 WAKE RD", "city": "WAKE", "state": "VA", "postal_code": "231762120", "telephone_number": "804-725-8597"}, {"country_code": "US", "country_name": "United States", "address_purpose": "LOCATION", "address_type": "DOM", "address_1": "2358 WAKE RD", "city": "WAKE", "state": "VA", "postal_code": "231762120", "telephone_number": "804-725-8597"}], "practiceLocations": [], "basic": {"organization_name": "ADDY'S COLORS", "organizational_subpart": "NO", "enumeration_date": "2022-07-07", "last_updated": "2022-07-07", "certification_date": "2022-07-07", "status": "A", "authorized_official_first_name": "AMANDA", "authorized_official_last_name": "ASHBURN", "authorized_official_telephone_number": "8047258597", "authorized_official_title_or_position": "CEO"}, "taxonomies": [{"code": "101YP2500X", "taxonomy_group": "193200000X - Multi-Specialty Group", "desc": "Counselor, Professional", "state": null, "license": null, "primary": true}], "identifiers": [], "endpoints": [{"endpointType": "DIRECT", "endpointTypeDescription": "Direct Messaging Address", "endpoint": "info@addyscolors.org", "endpointDescription": "Email", "affiliation": "N", "use": "DIRECT", "useDescription": "Direct", "contentTypeDescription": "", "country_code": "US", "country_name": "United States", "address_type": "DOM", "address_1": "2358 Wake Rd", "city": "Wake", "state": "VA", "postal_code": "231762120"}], "other_names": []}, {"created_epoch": "1687369274000", "enumeration_type": "NPI-1", "last_updated_epoch": "1687369274000", "number": "1831874353", "addresses": [{"country_code": "US", "country_name": "United States", "address_purpose": "LOCATION", "address_type": "DOM", "address_1": "312 BROWNS HILL CT", "city": "MIDLOTHIAN", "state": "VA", "postal_code": "231149511", "telephone_number": "804-893-5555"}, {"country_code": "US", "country_name": "United States", "address_purpose": "MAILING", "address_type": "DOM", "address_1": "287 SUGAR SHACK LN", "city": "WAKE", "state": "VA", "postal_code": "231762206"}], "practiceLocations": [], "basic": {"first_name": "TOSCA", "last_name": "LAHOCKI", "sole_proprietor": "NO", "gender": "F", "enumeration_date": "2023-06-21", "last_updated": "2023-06-21", "certification_date": "2023-06-21", "status": "A"}, "taxonomies": [{"code": "101YP2500X", "taxonomy_group": "", "desc": "Counselor, Professional", "state": "VA", "license": null, "primary": true}], "identifiers": [], "endpoints": [], "other_names": []}]