[{"created_epoch": "1735054204000", "enumeration_type": "NPI-2", "last_updated_epoch": "1735054204000", "number": "1205644150", "addresses": [{"country_code": "US", "country_name": "United States", "address_purpose": "MAILING", "address_type": "DOM", "address_1": "1811 JAMESTOWN RD", "city": "WILLIAMSBURG", "state": "VA", "postal_code": "231852326", "telephone_number": "757-229-9991", "fax_number": "757-229-9509"}, {"country_code": "US", "country_name": "United States", "address_purpose": "LOCATION", "address_type": "DOM", "address_1": "1811 JAMESTOWN RD", "city": "WILLIAMSBURG", "state": "VA", "postal_code": "231852326", "telephone_number": "757-229-9991", "fax_number": "757-229-9509"}], "practiceLocations": [], "basic": {"organization_name": "1811 JAMESTOWN ROAD OPCO LLC", "organizational_subpart": "NO", "enumeration_date": "2024-12-24", "last_updated": "2024-12-24", "certification_date": "2024-12-24", "status": "A", "authorized_official_first_name": "TIFFANY", "authorized_official_last_name": "HOBACK", "authorized_official_telephone_number": "7706989040", "authorized_official_title_or_position": "Manager"}, "taxonomies": [{"code": "314000000X", "taxonomy_group": "", "desc": "Skilled Nursing Facility", "state": null, "license": null, "primary": true}], "identifiers": [], "endpoints": [], "other_names": [{"organization_name": "JAMESTOWN HEALTH & REHABILITATION", "type": "Doing Business As", "code": "3"}]}, {"created_epoch": "1567196325000", "enumeration_type": "NPI-2", "last_updated_epoch": "1669729712000", "number": "1093363251", "addresses": [{"country_code": "US", "country_name": "United States", "address_purpose": "LOCATION", "address_type": "DOM", "address_1": "161-A JOHN JEFFERSON ROAD STE 101", "city": "WILLIAMSBURG", "state": "VA", "postal_code": "23185", "telephone_number": "757-496-2030", "fax_number": "757-496-0604"}, {"country_code": "US", "country_name": "United States", "address_purpose": "MAILING", "address_type": "DOM", "address_1": "3325 BARTLETT BLVD", "city": "ORLANDO", "state": "FL", "postal_code": "328116428", "telephone_number": "407-206-0040", "fax_number": "407-206-0010"}], "practiceLocations": [], "basic": {"organization_name": "1ST CHOICE IN-HOMECARE, INC.", "organizational_subpart": "YES", "parent_organization_legal_business_name": "AEROCARE HOLDINGS LLC", "enumeration_date": "2019-08-30", "last_updated": "2022-11-29", "certification_date": "2022-11-29", "status": "A", "authorized_official_first_name": "STEPHEN", "authorized_official_last_name": "GRIGGS", "authorized_official_middle_name": "P", "authorized_official_telephone_number": "4072060040", "authorized_official_title_or_position": "CEO, President"}, "taxonomies": [{"code": "332BX2000X", "taxonomy_group": "", "desc": "Durable Medical Equipment & Medical Supplies, Oxygen Equipment & Supplies", "state": null, "license": null, "primary": true}], "identifiers": [], "endpoints": [], "other_names": [{"organization_name": "AEROCARE SLEEP CENTER", "type": "Doing Business As", "code": "3"}]}, {"created_epoch": "1492535662000", "enumeration_type": "NPI-2", "last_updated_epoch": "1492535662000", "number": "1770017626", "addresses": [{"country_code": "US", "country_name": "United States", "address_purpose": "MAILING", "address_type": "DOM", "address_1": "3016 S CHASE", "city": "WILLIAMSBURG", "state": "VA", "postal_code": "231858732", "telephone_number": "940-206-1503"}, {"country_code": "US", "country_name": "United States", "address_purpose": "LOCATION", "address_type": "DOM", "address_1": "6632 GEORGE WASHINGTON MEM HWY", "city": "YORKTOWN", "state": "VA", "postal_code": "236924801", "telephone_number": "940-206-1503"}], "practiceLocations": [], "basic": {"organization_name": "AARON J IVERSON DDS, PLLC", "organizational_subpart": "NO", "enumeration_date": "2017-04-18", "last_updated": "2017-04-18", "status": "A", "authorized_official_first_name": "AARON", "authorized_official_last_name": "IVERSON", "authorized_official_middle_name": "JAMES", "authorized_official_telephone_number": "9402061503", "authorized_official_title_or_position": "Owner/Dentist", "authorized_official_name_prefix": "Dr.", "authorized_official_name_suffix": "--", "authorized_official_credential": "DDS"}, "taxonomies": [{"code": "122300000X", "taxonomy_group": "193400000X - Single Specialty Group", "desc": "Dentist", "state": "VA", "license": "0401415112", "primary": true}], "identifiers": [], "endpoints": [], "other_names": [{"organization_name": "IVERSON DENTAL CARE", "type": "Doing Business As", "code": "3"}]}, {"created_epoch": "1534550981000", "enumeration_type": "NPI-1", "last_updated_epoch": "1616612484000", "number": "1508346669", "addresses": [{"country_code": "US", "country_name": "United States", "address_purpose": "LOCATION", "address_type": "DOM", "address_1": "1158 PROFESSIONAL DR STE K", "city": "WILLIAMSBURG", "state": "VA", "postal_code": "231856618", "telephone_number": "703-498-8675"}, {"country_code": "US", "country_name": "United States", "address_purpose": "MAILING", "address_type": "DOM", "address_1": "1158 PROFESSIONAL DR STE K", "city": "WILLIAMSBURG", "state": "VA", "postal_code": "231856618", "telephone_number": "703-498-8675"}], "practiceLocations": [], "basic": {"first_name": "ROMINA", "last_name": "ABAWI-WOOTEN", "credential": "MA, CSAC, NCC", "sole_proprietor": "NO", "gender": "F", "enumeration_date": "2018-08-17", "last_updated": "2021-03-24", "certification_date": "2021-03-24", "status": "A"}, "taxonomies": [{"code": "101YA0400X", "taxonomy_group": "", "desc": "Counselor, Addiction (Substance Use Disorder)", "state": "VA", "license": "0710102735", "primary": false}, {"code": "101YM0800X", "taxonomy_group": "", "desc": "Counselor, Mental Health", "state": "VA", "license": "0701008810", "primary": true}], "identifiers": [], "endpoints": [], "other_names": []}, {"created_epoch": "1159454036000", "enumeration_type": "NPI-1", "last_updated_epoch": "1183947785000", "number": "1538250931", "addresses": [{"country_code": "US", "country_name": "United States", "address_purpose": "MAILING", "address_type": "DOM", "address_1": "1309 JAMESTOWN RD", "address_2": "STE. 101", "city": "WILLIAMSBURG", "state": "VA", "postal_code": "231853380", "telephone_number": "757-220-8800", "fax_number": "757-220-8811"}, {"country_code": "US", "country_name": "United States", "address_purpose": "LOCATION", "address_type": "DOM", "address_1": "1309 JAMESTOWN RD", "address_2": "STE. 101", "city": "WILLIAMSBURG", "state": "VA", "postal_code": "231853380", "telephone_number": "757-220-8800", "fax_number": "757-220-8811"}], "practiceLocations": [], "basic": {"first_name": "DIANE", "last_name": "ABDO", "credential": "PsyD", "sole_proprietor": "NO", "gender": "F", "enumeration_date": "2006-09-28", "last_updated": "2007-07-08", "status": "A", "name_prefix": "Dr.", "name_suffix": "--"}, "taxonomies": [{"code": "103TC0700X", "taxonomy_group": "", "desc": "Psychologist, Clinical", "state": "VA", "license": "0810-001755", "primary": true}], "identifiers": [{"code": "05", "desc": "MEDICAID", "issuer": null, "identifier": "5400236", "state": "VA"}], "endpoints": [], "other_names": []}, {"created_epoch": "1157673246000", "enumeration_type": "NPI-1", "last_updated_epoch": "1317755439000", "number": "1942304308", "addresses": [{"country_code": "US", "country_name": "United States", "address_purpose": "MAILING", "address_type": "DOM", "address_1": "1309 JAMESTOWN RD", "address_2": "STE. 101", "city": "WILLIAMSBURG", "state": "VA", "postal_code": "231853380", "telephone_number": "757-220-8800", "fax_number": "757-220-8811"}, {"country_code": "US", "country_name": "United States", "address_purpose": "LOCATION", "address_type": "DOM", "address_1": "1309 JAMESTOWN RD", "address_2": "STE. 101", "city": "WILLIAMSBURG", "state": "VA", "postal_code": "231853380", "telephone_number": "757-220-8800", "fax_number": "757-220-8811"}], "practiceLocations": [], "basic": {"first_name": "ROBERT", "last_name": "ABDO", "credential": "EdD", "sole_proprietor": "NO", "gender": "M", "enumeration_date": "2006-09-07", "last_updated": "2011-10-04", "status": "A", "name_prefix": "Dr.", "name_suffix": "--"}, "taxonomies": [{"code": "106H00000X", "taxonomy_group": "", "desc": "Marriage & Family Therapist", "state": "VA", "license": "0717-000004", "primary": true}, {"code": "101YM0800X", "taxonomy_group": "", "desc": "Counselor, Mental Health", "state": "VA", "license": "0701001162", "primary": false}], "identifiers": [], "endpoints": [], "other_names": []}, {"created_epoch": "1217605858000", "enumeration_type": "NPI-1", "last_updated_epoch": "1706559098000", "number": "1598921298", "addresses": [{"country_code": "US", "country_name": "United States", "address_purpose": "LOCATION", "address_type": "DOM", "address_1": "324 MONTICELLO AVE", "city": "WILLIAMSBURG", "state": "VA", "postal_code": "231852834", "telephone_number": "757-503-7917", "fax_number": "855-823-3243"}, {"country_code": "US", "country_name": "United States", "address_purpose": "MAILING", "address_type": "DOM", "address_1": "324 MONTICELLO AVE", "city": "WILLIAMSBURG", "state": "VA", "postal_code": "231852834", "telephone_number": "757-503-7916"}], "practiceLocations": [], "basic": {"first_name": "EVA", "last_name": "ABEL", "middle_name": "L", "credential": "Psy.D.", "sole_proprietor": "NO", "gender": "F", "enumeration_date": "2008-08-01", "last_updated": "2024-01-29", "certification_date": "2024-01-19", "status": "A"}, "taxonomies": [{"code": "103TC0700X", "taxonomy_group": "", "desc": "Psychologist, Clinical", "state": "VA", "license": "0810004226", "primary": true}], "identifiers": [{"code": "01", "desc": "Other (non-Medicare)", "issuer": "License number (for clinical psychologist)", "identifier": "0810004226", "state": "VA"}], "endpoints": [], "other_names": []}, {"created_epoch": "1216690996000", "enumeration_type": "NPI-1", "last_updated_epoch": "1370977338000", "number": "1982869715", "addresses": [{"country_code": "US", "country_name": "United States", "address_purpose": "MAILING", "address_type": "DOM", "address_1": "PO BOX 1239", "city": "TROY", "state": "MI", "postal_code": "480991239", "telephone_number": "248-824-6600", "fax_number": "248-324-1477"}, {"country_code": "US", "country_name": "United States", "address_purpose": "LOCATION", "address_type": "DOM", "address_1": "263 MCLAWS CIRCLE", "address_2": "SUITE 105", "city": "WILLIAMSBURG", "state": "VA", "postal_code": "231855629", "telephone_number": "757-941-5600", "fax_number": "757-564-0557"}], "practiceLocations": [], "basic": {"first_name": "RALPH", "last_name": "ABLASEAU", "middle_name": "KENNETH", "credential": "NP-C", "sole_proprietor": "NO", "gender": "M", "enumeration_date": "2008-07-21", "last_updated": "2013-06-11", "status": "A", "name_prefix": "Mr.", "name_suffix": "--"}, "taxonomies": [{"code": "363LF0000X", "taxonomy_group": "", "desc": "Nurse Practitioner, Family", "state": "VA", "license": "0024164829", "primary": false}, {"code": "363L00000X", "taxonomy_group": "", "desc": "Nurse Practitioner", "state": "VA", "license": "0024164829", "primary": true}], "identifiers": [{"code": "01", "desc": "Other (non-Medicare)", "issuer": "Tricare/Champus", "identifier": "-032", "state": "VA"}, {"code": "05", "desc": "MEDICAID", "issuer": null, "identifier": "1982869715", "state": "VA"}, {"code": "01", "desc": "Other (non-Medicare)", "issuer": "CorVel", "identifier": "PAR", "state": "VA"}, {"code": "01", "desc": "Other (non-Medicare)", "issuer": "USA Managed Care", "identifier": "PAR", "state": "VA"}, {"code": "01", "desc": "Other (non-Medicare)", "issuer": "MultiPlan", "identifier": "PAR", "state": "VA"}], "endpoints": [], "other_names": []}, {"created_epoch": "1488833814000", "enumeration_type": "NPI-2", "last_updated_epoch": "1700602437000", "number": "1942740279", "addresses": [{"country_code": "US", "country_name": "United States", "address_purpose": "LOCATION", "address_type": "DOM", "address_1": "5248 OLDE TOWNE RD STE 10", "city": "WILLIAMSBURG", "state": "VA", "postal_code": "231881986", "telephone_number": "757-603-4603"}, {"country_code": "US", "country_name": "United States", "address_purpose": "MAILING", "address_type": "DOM", "address_1": "5504 WESTMORELAND DR", "city": "WILLIAMSBURG", "state": "VA", "postal_code": "231888114", "telephone_number": "757-603-4603"}], "practiceLocations": [{"country_code": "US", "country_name": "United States", "address_purpose": "LOCATION", "address_type": "DOM", "address_1": "1315 JAMESTOWN RD STE 203", "city": "WILLIAMSBURG", "state": "VA", "postal_code": "231853303", "telephone_number": "757-603-4603"}, {"country_code": "US", "country_name": "United States", "address_purpose": "LOCATION", "address_type": "DOM", "address_1": "8545 PATTERSON AVE STE 301", "city": "HENRICO", "state": "VA", "postal_code": "232296455", "telephone_number": "757-603-4603"}, {"country_code": "US", "country_name": "United States", "address_purpose": "LOCATION", "address_type": "DOM", "address_1": "1001 RICHMOND RD", "city": "WILLIAMSBURG", "state": "VA", "postal_code": "231852895", "telephone_number": "757-603-4603"}, {"country_code": "US", "country_name": "United States", "address_purpose": "LOCATION", "address_type": "DOM", "address_1": "501 PRINCE GEORGE ST", "city": "WILLIAMSBURG", "state": "VA", "postal_code": "231853664", "telephone_number": "757-603-4603"}], "basic": {"organization_name": "ABUNDANT LIFE PARTNERS, LLC", "organizational_subpart": "NO", "enumeration_date": "2017-03-06", "last_updated": "2023-11-21", "certification_date": "2023-11-21", "status": "A", "authorized_official_first_name": "MEGHAN", "authorized_official_last_name": "FREEMAN", "authorized_official_telephone_number": "5408415784", "authorized_official_title_or_position": "SOLE PROPRIETOR", "authorized_official_name_prefix": "--", "authorized_official_name_suffix": "--", "authorized_official_credential": "LCSW"}, "taxonomies": [{"code": "1041C0700X", "taxonomy_group": "193400000X - Single Specialty Group", "desc": "Social Worker, Clinical", "state": "VA", "license": "0904009742", "primary": true}], "identifiers": [], "endpoints": [], "other_names": []}, {"created_epoch": "1479752340000", "enumeration_type": "NPI-2", "last_updated_epoch": "1479752340000", "number": "1023551207", "addresses": [{"country_code": "US", "country_name": "United States", "address_purpose": "MAILING", "address_type": "DOM", "address_1": "1769 JAMESTOWN RD", "address_2": "SUITE 1B", "city": "WILLIAMSBURG", "state": "VA", "postal_code": "231852324", "telephone_number": "757-897-1833", "fax_number": "757-273-1133"}, {"country_code": "US", "country_name": "United States", "address_purpose": "LOCATION", "address_type": "DOM", "address_1": "1769 JAMESTOWN RD", "address_2": "SUITE 1B", "city": "WILLIAMSBURG", "state": "VA", "postal_code": "231852324", "telephone_number": "757-897-1833", "fax_number": "757-273-1133"}], "practiceLocations": [], "basic": {"organization_name": "ACCESS CHILD AND FAMILY CARE", "organizational_subpart": "NO", "enumeration_date": "2016-11-21", "last_updated": "2016-11-21", "status": "A", "authorized_official_first_name": "JEANNE", "authorized_official_last_name": "CORNETT", "authorized_official_middle_name": "SOVEK", "authorized_official_telephone_number": "7578971833", "authorized_official_title_or_position": "Owner/Director", "authorized_official_name_prefix": "--", "authorized_official_name_suffix": "--"}, "taxonomies": [{"code": "251C00000X", "taxonomy_group": "", "desc": "Day Training, Developmentally Disabled Services", "state": null, "license": null, "primary": true}], "identifiers": [], "endpoints": [], "other_names": []}, {"created_epoch": "1463880940000", "enumeration_type": "NPI-2", "last_updated_epoch": "1463880940000", "number": "1225485030", "addresses": [{"country_code": "US", "country_name": "United States", "address_purpose": "MAILING", "address_type": "DOM", "address_1": "1769 JAMESTOWN RD", "address_2": "SUITE 1B", "city": "WILLIAMSBURG", "state": "VA", "postal_code": "231852324", "telephone_number": "757-525-2595", "fax_number": "757-273-1133"}, {"country_code": "US", "country_name": "United States", "address_purpose": "LOCATION", "address_type": "DOM", "address_1": "1769 JAMESTOWN RD", "address_2": "SUITE 1B", "city": "WILLIAMSBURG", "state": "VA", "postal_code": "231852324", "telephone_number": "757-525-2595", "fax_number": "757-273-1133"}], "practiceLocations": [], "basic": {"organization_name": "ACCESS CHILD AND FAMILY CARE INC", "organizational_subpart": "NO", "enumeration_date": "2016-05-21", "last_updated": "2016-05-21", "status": "A", "authorized_official_first_name": "JEANNE", "authorized_official_last_name": "CORNETT", "authorized_official_middle_name": "SOVEK", "authorized_official_telephone_number": "7575252595", "authorized_official_title_or_position": "Executive Director", "authorized_official_name_prefix": "--", "authorized_official_name_suffix": "--", "authorized_official_credential": "RN"}, "taxonomies": [{"code": "251B00000X", "taxonomy_group": "", "desc": "Case Management", "state": null, "license": null, "primary": false}, {"code": "251V00000X", "taxonomy_group": "", "desc": "Voluntary or Charitable", "state": null, "license": null, "primary": true}], "identifiers": [], "endpoints": [], "other_names": []}, {"created_epoch": "1312310047000", "enumeration_type": "NPI-2", "last_updated_epoch": "1372294634000", "number": "1407134885", "addresses": [{"country_code": "US", "country_name": "United States", "address_purpose": "MAILING", "address_type": "DOM", "address_1": "3021 CAMROSE DR", "address_2": "SUITE 100", "city": "WILLIAMSBURG", "state": "VA", "postal_code": "231858712", "telephone_number": "757-525-2595", "fax_number": "757-273-1133"}, {"country_code": "US", "country_name": "United States", "address_purpose": "LOCATION", "address_type": "DOM", "address_1": "3021 CAMROSE DR", "address_2": "SUITE 100", "city": "WILLIAMSBURG", "state": "VA", "postal_code": "231858712", "telephone_number": "757-525-2595", "fax_number": "757-273-1133"}], "practiceLocations": [], "basic": {"organization_name": "ACCESS FAMILY CARE", "organizational_subpart": "NO", "enumeration_date": "2011-08-02", "last_updated": "2013-06-26", "status": "A", "authorized_official_first_name": "JEANNE", "authorized_official_last_name": "CORNETT", "authorized_official_middle_name": "SOVEK", "authorized_official_telephone_number": "7575252595", "authorized_official_title_or_position": "Care Coordinator", "authorized_official_name_prefix": "--", "authorized_official_name_suffix": "--", "authorized_official_credential": "RN"}, "taxonomies": [{"code": "251B00000X", "taxonomy_group": "", "desc": "Case Management", "state": "VA", "license": "0001193123", "primary": true}], "identifiers": [], "endpoints": [], "other_names": []}, {"created_epoch": "1466207237000", "enumeration_type": "NPI-2", "last_updated_epoch": "1466207237000", "number": "1952751158", "addresses": [{"country_code": "US", "country_name": "United States", "address_purpose": "MAILING", "address_type": "DOM", "address_1": "1769 JAMESTOWN RD", "address_2": "STE 1B", "city": "WILLIAMSBURG", "state": "VA", "postal_code": "231852324", "telephone_number": "757-585-3318"}, {"country_code": "US", "country_name": "United States", "address_purpose": "LOCATION", "address_type": "DOM", "address_1": "1769 JAMESTOWN RD", "address_2": "STE 1B", "city": "WILLIAMSBURG", "state": "VA", "postal_code": "231852324", "telephone_number": "757-585-3318"}], "practiceLocations": [], "basic": {"organization_name": "ACCESS FAMILY SUPPORT", "organizational_subpart": "NO", "enumeration_date": "2016-06-17", "last_updated": "2016-06-17", "status": "A", "authorized_official_first_name": "KATHY", "authorized_official_last_name": "SAUTER", "authorized_official_telephone_number": "7575853318", "authorized_official_title_or_position": "Case Management Services", "authorized_official_name_prefix": "Mrs.", "authorized_official_name_suffix": "--"}, "taxonomies": [{"code": "251B00000X", "taxonomy_group": "", "desc": "Case Management", "state": null, "license": null, "primary": true}], "identifiers": [], "endpoints": [], "other_names": []}, {"created_epoch": "1372437176000", "enumeration_type": "NPI-2", "last_updated_epoch": "1372437176000", "number": "1710327267", "addresses": [{"country_code": "US", "country_name": "United States", "address_purpose": "MAILING", "address_type": "DOM", "address_1": "3021 CAMROSE DR", "address_2": "SUITE 100", "city": "WILLIAMSBURG", "state": "VA", "postal_code": "231858712", "telephone_number": "757-525-2595", "fax_number": "757-273-1133"}, {"country_code": "US", "country_name": "United States", "address_purpose": "LOCATION", "address_type": "DOM", "address_1": "3021 CAMROSE DR", "address_2": "SUITE 100", "city": "WILLIAMSBURG", "state": "VA", "postal_code": "231858712", "telephone_number": "757-525-2595", "fax_number": "757-273-1133"}], "practiceLocations": [], "basic": {"organization_name": "ACCESS PEDIATRIC CARE", "organizational_subpart": "YES", "parent_organization_legal_business_name": "ACCESS FAMILY CARE", "enumeration_date": "2013-06-28", "last_updated": "2013-06-28", "status": "A", "authorized_official_first_name": "JEANNE", "authorized_official_last_name": "CORNETT", "authorized_official_middle_name": "SOVEK", "authorized_official_telephone_number": "7575252595", "authorized_official_title_or_position": "Director", "authorized_official_name_prefix": "Mrs.", "authorized_official_name_suffix": "--", "authorized_official_credential": "RN"}, "taxonomies": [{"code": "251B00000X", "taxonomy_group": "", "desc": "Case Management", "state": "VA", "license": "0001193123", "primary": true}], "identifiers": [], "endpoints": [], "other_names": [{"organization_name": "ACCESS PEDIATRIC CARE", "type": "Doing Business As", "code": "3"}]}, {"created_epoch": "1126709198000", "enumeration_type": "NPI-1", "last_updated_epoch": "1379944950000", "number": "1194710335", "addresses": [{"country_code": "US", "country_name": "United States", "address_purpose": "LOCATION", "address_type": "DOM", "address_1": "120 KINGS WAY", "address_2": "SUITE 2200", "city": "WILLIAMSBURG", "state": "VA", "postal_code": "23185", "telephone_number": "757-645-3460", "fax_number": "757-645-3481"}, {"country_code": "US", "country_name": "United States", "address_purpose": "MAILING", "address_type": "DOM", "address_1": "856 J CLYDE MORRIS BLVD", "address_2": "SUITE A", "city": "NEWPORT NEWS", "state": "VA", "postal_code": "23601"}], "practiceLocations": [], "basic": {"first_name": "RICHARD", "last_name": "ACKART", "credential": "MD", "sole_proprietor": "NO", "gender": "M", "enumeration_date": "2005-09-14", "last_updated": "2013-09-23", "status": "A", "name_prefix": "--", "name_suffix": "--"}, "taxonomies": [{"code": "207RP1001X", "taxonomy_group": "", "desc": "Internal Medicine, Pulmonary Disease", "state": "VA", "license": "0101026241", "primary": true}, {"code": "207R00000X", "taxonomy_group": "", "desc": "Internal Medicine", "state": "VA", "license": "0101026241", "primary": false}], "identifiers": [{"code": "05", "desc": "MEDICAID", "issuer": null, "identifier": "1194710335", "state": "VA"}], "endpoints": [], "other_names": []}, {"created_epoch": "1729728304000", "enumeration_type": "NPI-2", "last_updated_epoch": "1731103106000", "number": "1790506533", "addresses": [{"country_code": "US", "country_name": "United States", "address_purpose": "LOCATION", "address_type": "DOM", "address_1": "1162 PROFESSIONAL DR", "city": "WILLIAMSBURG", "state": "VA", "postal_code": "231853330", "telephone_number": "757-345-3100"}, {"country_code": "US", "country_name": "United States", "address_purpose": "MAILING", "address_type": "DOM", "address_1": "1162 PROFESSIONAL DR", "city": "WILLIAMSBURG", "state": "VA", "postal_code": "231853330", "telephone_number": "757-345-3100"}], "practiceLocations": [], "basic": {"organization_name": "ACT OF VIRGINIA", "organizational_subpart": "NO", "enumeration_date": "2024-10-23", "last_updated": "2024-11-08", "certification_date": "2024-11-08", "status": "A", "authorized_official_first_name": "ANN", "authorized_official_last_name": "VANSKIVER", "authorized_official_middle_name": "P", "authorized_official_telephone_number": "7573453100", "authorized_official_title_or_position": "CEO/Owner", "authorized_official_credential": "Psy.D., ABSNP"}, "taxonomies": [{"code": "103TC0700X", "taxonomy_group": "193200000X - Multi-Specialty Group", "desc": "Psychologist, Clinical", "state": null, "license": null, "primary": true}], "identifiers": [], "endpoints": [], "other_names": []}, {"created_epoch": "1737741302000", "enumeration_type": "NPI-2", "last_updated_epoch": "1737741302000", "number": "1255143327", "addresses": [{"country_code": "US", "country_name": "United States", "address_purpose": "MAILING", "address_type": "DOM", "address_1": "PO BOX 269068", "city": "OKLAHOMA CITY", "state": "OK", "postal_code": "731269068", "telephone_number": "757-253-2393", "fax_number": "757-259-0433"}, {"country_code": "US", "country_name": "United States", "address_purpose": "LOCATION", "address_type": "DOM", "address_1": "1323 JAMESTOWN RD STE 203", "city": "WILLIAMSBURG", "state": "VA", "postal_code": "231853367", "telephone_number": "757-253-2393", "fax_number": "757-259-0433"}], "practiceLocations": [], "basic": {"organization_name": "ADAM E. SCHMIDT DDS", "organizational_subpart": "NO", "enumeration_date": "2025-01-24", "last_updated": "2025-01-24", "certification_date": "2025-01-24", "status": "A", "authorized_official_first_name": "ADAM", "authorized_official_last_name": "SCHMIDT", "authorized_official_middle_name": "E", "authorized_official_telephone_number": "7572532393", "authorized_official_title_or_position": "Owner", "authorized_official_credential": "DDS"}, "taxonomies": [{"code": "1223S0112X", "taxonomy_group": "193400000X - Single Specialty Group", "desc": "Dentist, Oral and Maxillofacial Surgery", "state": null, "license": null, "primary": true}], "identifiers": [], "endpoints": [], "other_names": []}, {"created_epoch": "1156281788000", "enumeration_type": "NPI-2", "last_updated_epoch": "1294861699000", "number": "1255447033", "addresses": [{"country_code": "US", "country_name": "United States", "address_purpose": "MAILING", "address_type": "DOM", "address_1": "140 PROFESSIONAL CIR", "city": "WILLIAMSBURG", "state": "VA", "postal_code": "231853374", "telephone_number": "757-220-9670", "fax_number": "757-564-1197"}, {"country_code": "US", "country_name": "United States", "address_purpose": "LOCATION", "address_type": "DOM", "address_1": "140 PROFESSIONAL CIR", "city": "WILLIAMSBURG", "state": "VA", "postal_code": "231853374", "telephone_number": "757-220-9670", "fax_number": "757-564-1197"}], "practiceLocations": [], "basic": {"organization_name": "ADAM L. WILDING, D.C., P.C.", "organizational_subpart": "NO", "enumeration_date": "2006-08-22", "last_updated": "2011-01-12", "status": "A", "authorized_official_first_name": "ADAM", "authorized_official_last_name": "WILDING", "authorized_official_middle_name": "LEWIS", "authorized_official_telephone_number": "7572209670", "authorized_official_title_or_position": "Chiropractor", "authorized_official_name_prefix": "Dr.", "authorized_official_name_suffix": "--", "authorized_official_credential": "D.C."}, "taxonomies": [{"code": "111N00000X", "taxonomy_group": "193400000X - Single Specialty Group", "desc": "Chiropractor", "state": "VA", "license": "0104002050", "primary": true}], "identifiers": [{"code": "01", "desc": "Other (non-Medicare)", "issuer": "CAQH Network", "identifier": "10390667", "state": "VA"}, {"code": "01", "desc": "Other (non-Medicare)", "issuer": "Anthem", "identifier": "143000", "state": "VA"}, {"code": "01", "desc": "Other (non-Medicare)", "issuer": "VHN", "identifier": "20014200", "state": "VA"}, {"code": "01", "desc": "Other (non-Medicare)", "issuer": "Cigna", "identifier": "3182289", "state": "VA"}, {"code": "01", "desc": "Other (non-Medicare)", "issuer": "Aetna", "identifier": "7223005", "state": "VA"}, {"code": "01", "desc": "Other (non-Medicare)", "issuer": "First Health", "identifier": "=========", "state": "VA"}, {"code": "01", "desc": "Other (non-Medicare)", "issuer": "ACN", "identifier": "=========", "state": "VA"}, {"code": "01", "desc": "Other (non-Medicare)", "issuer": "PHCS", "identifier": "=========", "state": "VA"}, {"code": "01", "desc": "Other (non-Medicare)", "issuer": "Railroad Medicare Group #", "identifier": "DC3738", "state": "VA"}], "endpoints": [], "other_names": [{"organization_name": "COMMONWEALTH FAMILY CHIROPRACTIC", "type": "Doing Business As", "code": "3"}]}, {"created_epoch": "1160005520000", "enumeration_type": "NPI-2", "last_updated_epoch": "1318882540000", "number": "1003902685", "addresses": [{"country_code": "US", "country_name": "United States", "address_purpose": "MAILING", "address_type": "DOM", "address_1": "1309 JAMESTOWN RD", "address_2": "STE. 101", "city": "WILLIAMSBURG", "state": "VA", "postal_code": "231853380", "telephone_number": "757-220-8800", "fax_number": "757-220-8811"}, {"country_code": "US", "country_name": "United States", "address_purpose": "LOCATION", "address_type": "DOM", "address_1": "1309 JAMESTOWN RD", "address_2": "STE. 101", "city": "WILLIAMSBURG", "state": "VA", "postal_code": "231853380", "telephone_number": "757-220-8800", "fax_number": "757-220-8811"}], "practiceLocations": [], "basic": {"organization_name": "ADR CLINICAL ASSOCIATES, INC.", "organizational_subpart": "NO", "enumeration_date": "2006-10-04", "last_updated": "2011-10-17", "status": "A", "authorized_official_first_name": "ROBERT", "authorized_official_last_name": "ABDO", "authorized_official_telephone_number": "7572208800", "authorized_official_title_or_position": "President", "authorized_official_name_prefix": "Dr.", "authorized_official_name_suffix": "--", "authorized_official_credential": "EdD"}, "taxonomies": [{"code": "103TC0700X", "taxonomy_group": "193400000X - Single Specialty Group", "desc": "Psychologist, Clinical", "state": null, "license": null, "primary": true}], "identifiers": [], "endpoints": [], "other_names": []}, {"created_epoch": "1140219091000", "enumeration_type": "NPI-1", "last_updated_epoch": "1638477499000", "number": "1437124039", "addresses": [{"country_code": "US", "country_name": "United States", "address_purpose": "LOCATION", "address_type": "DOM", "address_1": "577 STERNBERG AVE", "address_2": "HQ USADENTAC CREDENTIALS OFFICE", "city": "FORT EUSTIS", "state": "VA", "postal_code": "236041526", "telephone_number": "757-314-7980"}, {"country_code": "US", "country_name": "United States", "address_purpose": "MAILING", "address_type": "DOM", "address_1": "2700 WINGFIELD CLOSE", "city": "WILLIAMSBURG", "state": "VA", "postal_code": "231857518", "telephone_number": "757-258-1531"}], "practiceLocations": [], "basic": {"first_name": "ERIC", "last_name": "ADRIAN", "middle_name": "DEAN", "credential": "DMD", "sole_proprietor": "NO", "gender": "M", "enumeration_date": "2006-02-17", "last_updated": "2021-12-02", "certification_date": "2021-12-02", "status": "A", "name_prefix": "Dr."}, "taxonomies": [{"code": "1223P0700X", "taxonomy_group": "", "desc": "Dentist, Prosthodontics", "state": "VA", "license": "0401008107", "primary": true}], "identifiers": [], "endpoints": [], "other_names": []}]